{"data_mtime":1764598571,"dep_hashes":["bee6f1eb19ee0fecac21a0b302722ca8289c1b2e"],"dep_lines":[1],"dep_prios":[5],"dependencies":["builtins"],"error_lines":[],"hash":"da39a3ee5e6b4b0d3255bfef95601890afd80709","id":"httpcore._backends","ignore_all":true,"interface_hash":"87217ee4db6620faa3f1aa3f3abaf1a9d2d7a393","mtime":1764487562,"options":{"other_options":"f30179ebc123614367a6d69de729ec1487b98dd5","platform":"win32"},"path":"F:\\my-ai-book\\my-ai-spec-book\\backend\\.venv\\Lib\\site-packages\\httpcore\\_backends\\__init__.py","plugin_data":null,"size":0,"suppressed":[],"version_id":"1.19.0"}